odoo/addons/account_fiscal_year/README.rst
odoo/addons/account_fiscal_year/__init__.py
odoo/addons/account_fiscal_year/__manifest__.py
odoo/addons/account_fiscal_year/data/date_range_type.xml
odoo/addons/account_fiscal_year/i18n/account_fiscal_year.pot
odoo/addons/account_fiscal_year/i18n/ca.po
odoo/addons/account_fiscal_year/i18n/ca_ES.po
odoo/addons/account_fiscal_year/i18n/da.po
odoo/addons/account_fiscal_year/i18n/da_DK.po
odoo/addons/account_fiscal_year/i18n/de.po
odoo/addons/account_fiscal_year/i18n/es.po
odoo/addons/account_fiscal_year/i18n/fr.po
odoo/addons/account_fiscal_year/i18n/hr.po
odoo/addons/account_fiscal_year/i18n/it.po
odoo/addons/account_fiscal_year/i18n/nl.po
odoo/addons/account_fiscal_year/i18n/pt.po
odoo/addons/account_fiscal_year/i18n/sl.po
odoo/addons/account_fiscal_year/readme/CONTRIBUTORS.rst
odoo/addons/account_fiscal_year/readme/DESCRIPTION.rst
odoo/addons/account_fiscal_year/static/description/icon.png
odoo/addons/account_fiscal_year/static/description/index.html
odoo/addons/account_fiscal_year/views/account_views.xml
odoo12_addon_account_fiscal_year-12.0.1.0.1.dist-info/METADATA
odoo12_addon_account_fiscal_year-12.0.1.0.1.dist-info/WHEEL
odoo12_addon_account_fiscal_year-12.0.1.0.1.dist-info/top_level.txt
odoo12_addon_account_fiscal_year-12.0.1.0.1.dist-info/RECORD
