Metadata-Version: 2.1
Name: odoo12-addon-account-fiscal-year
Version: 12.0.1.0.1
Summary: Create a menu for Account Fiscal Year
Home-page: https://github.com/OCA/account-financial-tools
Author: Agile Business Group, Camptocamp SA, Odoo Community Association (OCA)
Author-email: support@odoo-community.org
License: LGPL-3
Platform: UNKNOWN
Classifier: Programming Language :: Python
Classifier: Framework :: Odoo
Classifier: Framework :: Odoo :: 12.0
Classifier: License :: OSI Approved :: GNU Lesser General Public License v3 (LGPLv3)
Classifier: Development Status :: 5 - Production/Stable
Requires-Python: >=3.5
Requires-Dist: odoo12-addon-date-range
Requires-Dist: odoo (<12.1dev,>=12.0a)
